molid/__init__.py
molid/__main__.py
molid/cli.py
molid/main.py
molid/pipeline.py
molid/db/__init__.py
molid/db/cas_enrich.py
molid/db/db_utils.py
molid/db/offline_db_cli.py
molid/db/schema.py
molid/db/sqlite_manager.py
molid/pubchemproc/__init__.py
molid/pubchemproc/cache.py
molid/pubchemproc/fetch.py
molid/pubchemproc/file_handler.py
molid/pubchemproc/pubchem.py
molid/pubchemproc/pubchem_client.py
molid/search/__init__.py
molid/search/db_lookup.py
molid/search/service.py
molid/utils/__init__.py
molid/utils/conversion.py
molid/utils/disk_utils.py
molid/utils/formula.py
molid/utils/ftp_utils.py
molid/utils/identifiers.py
molid/utils/settings.py
molid-0.8.4.dist-info/licenses/LICENSE
molid-0.8.4.dist-info/METADATA
molid-0.8.4.dist-info/WHEEL
molid-0.8.4.dist-info/entry_points.txt
molid-0.8.4.dist-info/top_level.txt
molid-0.8.4.dist-info/RECORD
