Metadata-Version: 2.4
Name: molid
Version: 0.8.4
Summary: A package for processing PubChem data and managing a database of chemical compounds.
Author-email: Thea Denell <thea.denell@physik.hu-berlin.de>
License:                                  Apache License
Classifier: Intended Audience :: Developers
Classifier: Topic :: Scientific/Engineering :: Physics
Classifier: License :: OSI Approved :: Apache Software License
Classifier: Programming Language :: Python
Classifier: Programming Language :: Python :: 3
Classifier: Programming Language :: Python :: 3 :: Only
Classifier: Operating System :: OS Independent
Requires-Python: >=3.8
License-File: LICENSE
Requires-Dist: click>=8.0
Requires-Dist: ase>=1.1.7
Requires-Dist: appdirs>=1.4
Requires-Dist: psutil==6.1.1
Requires-Dist: pydantic>=2.0
Requires-Dist: pydantic-settings>=2.0
Requires-Dist: requests>=2.20.0
Requires-Dist: tqdm
Requires-Dist: psutil
Provides-Extra: tests
Requires-Dist: pytest; extra == "tests"
Provides-Extra: openbabel
Requires-Dist: openbabel-wheel; extra == "openbabel"
Dynamic: license-file
